jmeter_compare/__init__.py
jmeter_compare/__main__.py
jmeter_compare/main.py
tests/__init__.py
tests/test_jmeter_compare.py
jmeter_compare-1.1.0.dist-info/METADATA
jmeter_compare-1.1.0.dist-info/WHEEL
jmeter_compare-1.1.0.dist-info/entry_points.txt
jmeter_compare-1.1.0.dist-info/top_level.txt
jmeter_compare-1.1.0.dist-info/RECORD
