Metadata-Version: 2.1
Name: jmeter_compare
Version: 1.1.0
Summary: This runs my script which is great.
Author: Me
Requires-Python: >=3.5
Requires-Dist: setuptools
Requires-Dist: matplotlib >=3.9.0
Requires-Dist: pandas >=0.22.0
Requires-Dist: numpy >=1.16.0
